GrobidArticleExtractor/__init__.py
GrobidArticleExtractor/app.py
GrobidArticleExtractor/cli.py
grobidarticleextractor-0.7.0.dist-info/LICENSE.txt
grobidarticleextractor-0.7.0.dist-info/METADATA
grobidarticleextractor-0.7.0.dist-info/WHEEL
grobidarticleextractor-0.7.0.dist-info/entry_points.txt
grobidarticleextractor-0.7.0.dist-info/RECORD
