Metadata-Version: 2.1
Name: GrobidArticleExtractor
Version: 0.7.0
Summary: GrobidArticleExtractor is a Python package designed to extract and organize content from scientific papers in PDF format.
Home-page: https://github.com/sensein/GrobidArticleExtractor
License: MIT
Keywords: python,package,template
Author: tekrajchhetri
Author-email: tekrajchhetri@gmail.com
Maintainer: tekrajchhetri
Maintainer-email: tekrajchhetri@gmail.com
Requires-Python: >=3.10,<4.0
Classifier: Development Status :: 4 - Beta
Classifier: License :: OSI Approved :: MIT License
Classifier: Operating System :: OS Independent
Classifier: Programming Language :: Python :: 3
Classifier: Programming Language :: Python :: 3.10
Classifier: Programming Language :: Python :: 3.11
Classifier: Programming Language :: Python :: 3.12
Requires-Dist: click (>=8.1.7,<9.0.0)
Requires-Dist: lxml (>=5.3.0,<6.0.0)
Requires-Dist: pathlib (>=1.0.1,<2.0.0)
Requires-Dist: pytest (>=8.3.4,<9.0.0)
Requires-Dist: requests (>=2.32.3,<3.0.0)
Project-URL: Documentation, https://tekrajchhetri.github.io/GrobidArticleExtractor
Project-URL: Repository, https://github.com/sensein/GrobidArticleExtractor
